pytket/extensions/azure/__init__.py
pytket/extensions/azure/_metadata.py
pytket/extensions/azure/py.typed
pytket/extensions/azure/backends/__init__.py
pytket/extensions/azure/backends/azure.py
pytket/extensions/azure/backends/config.py
pytket_azure-0.5.1.dist-info/licenses/LICENSE
pytket_azure-0.5.1.dist-info/METADATA
pytket_azure-0.5.1.dist-info/WHEEL
pytket_azure-0.5.1.dist-info/top_level.txt
pytket_azure-0.5.1.dist-info/RECORD
