Metadata-Version: 2.4
Name: pytket-azure
Version: 0.5.1
Summary: Extension for pytket, providing access to Azure devices
Author: TKET development team
Author-email: tket-support@quantinuum.com
License: Apache 2
Project-URL: Documentation, https://tket.quantinuum.com/extensions/pytket-azure/index.html
Project-URL: Source, https://github.com/CQCL/pytket-azure
Project-URL: Tracker, https://github.com/CQCL/pytket-azure/issues
Classifier: Environment :: Console
Classifier: Programming Language :: Python :: 3.10
Classifier: Programming Language :: Python :: 3.11
Classifier: Programming Language :: Python :: 3.12
Classifier: License :: OSI Approved :: Apache Software License
Classifier: Operating System :: MacOS :: MacOS X
Classifier: Operating System :: POSIX :: Linux
Classifier: Operating System :: Microsoft :: Windows
Classifier: Intended Audience :: Developers
Classifier: Intended Audience :: Science/Research
Classifier: Topic :: Scientific/Engineering
Requires-Python: >=3.10
License-File: LICENSE
Requires-Dist: azure-quantum>=3.1.0
Requires-Dist: pytket>=2.2.0
Requires-Dist: pytket-qir>=0.22.0
Dynamic: author
Dynamic: author-email
Dynamic: classifier
Dynamic: description
Dynamic: description-content-type
Dynamic: license
Dynamic: license-file
Dynamic: project-url
Dynamic: requires-dist
Dynamic: requires-python
Dynamic: summary
